tree_sitter_rtx-1.2.1.dist-info/RECORD
tree_sitter_rtx-1.2.1.dist-info/top_level.txt
tree_sitter_rtx-1.2.1.dist-info/METADATA
tree_sitter_rtx-1.2.1.dist-info/WHEEL
tree_sitter_rtx/__init__.pyi
tree_sitter_rtx/_binding.abi3.so
tree_sitter_rtx/py.typed
tree_sitter_rtx/binding.c
tree_sitter_rtx/__init__.py
tree_sitter_rtx/queries/tags.scm
tree_sitter_rtx/queries/highlights.scm
