Metadata-Version: 2.1
Name: tree-sitter-rtx
Version: 1.2.1
Summary: tree-sitter parser of Apertium-recursive rule files.
Author: Daniel Swanson
License: GPL-3.0-or-later
Project-URL: Homepage, https://github.com/apertium/tree-sitter-apertium
Keywords: incremental,parsing,tree-sitter,rtx
Classifier: Intended Audience :: Developers
Classifier: Topic :: Software Development :: Compilers
Classifier: Topic :: Text Processing :: Linguistic
Classifier: Typing :: Typed
Requires-Python: >=3.9
Provides-Extra: core
Requires-Dist: tree-sitter ~=0.22 ; extra == 'core'
